klay/__init__.py
klay/compile.py
klay/jax/__init__.py
klay/jax/semiring/__init__.py
klay/jax/semiring/godel.py
klay/jax/semiring/log.py
klay/jax/semiring/real.py
klay/nanobind_ext.cp310-win_amd64.pyd
klay/torch/__init__.py
klay/utils.py
klaycircuits-0.0.3.dist-info/METADATA
klaycircuits-0.0.3.dist-info/WHEEL
klaycircuits-0.0.3.dist-info/licenses/LICENSE
klaycircuits-0.0.3.dist-info/RECORD
