Metadata-Version: 2.1
Name: klaycircuits
Version: 0.0.3
Summary: Arithmetic circuits on the GPU
Author: Jaron Maene, Vincent Derkinderen, Pedro Zuidberg Dos Martires
Classifier: License :: OSI Approved :: Apache Software License
Project-URL: Homepage, https://github.com/ML-KULeuven/klay
Requires-Python: >=3.10
Requires-Dist: numpy
Provides-Extra: torch
Requires-Dist: torch; extra == "torch"
Provides-Extra: jax
Requires-Dist: jax; extra == "jax"
